junevis/__init__.py
junevis/_nbdev.py
junevis/create_project.py
junevis/path_fixes.py
junevis/process_loggers.py
junevis/record_reader.py
junevis/server.py
junevis/client/dist/favicon.ico
junevis/client/dist/index.html
junevis/client/dist/demo/availableProjects.txt
junevis/client/dist/demo/projects/learning_centers/metadata.json
junevis/client/dist/demo/projects/learning_centers/sites.geojson
junevis/client/dist/demo/projects/learning_centers/summary_001.csv
junevis/client/dist/demo/projects/learning_centers/summary_002.csv
junevis/client/dist/demo/projects/learning_centers/summary_003.csv
junevis/client/dist/demo/projects/learning_centers/summary_004.csv
junevis/client/dist/demo/projects/learning_centers/summary_005.csv
junevis/client/dist/demo/projects/learning_centers/summary_006.csv
junevis/client/dist/demo/projects/learning_centers/summary_007.csv
junevis/client/dist/demo/projects/learning_centers/summary_008.csv
junevis/client/dist/demo/projects/learning_centers/summary_009.csv
junevis/client/dist/demo/projects/learning_centers/summary_010.csv
junevis/client/dist/demo/projects/mask_wearing/metadata.json
junevis/client/dist/demo/projects/mask_wearing/sites.geojson
junevis/client/dist/demo/projects/mask_wearing/summary_000.csv
junevis/client/dist/demo/projects/mask_wearing/summary_001.csv
junevis/client/dist/demo/projects/mask_wearing/summary_002.csv
junevis/client/dist/demo/projects/mask_wearing/summary_003.csv
junevis/client/dist/demo/projects/mask_wearing/summary_004.csv
junevis/client/dist/demo/projects/mask_wearing/summary_005.csv
junevis/client/dist/demo/projects/mask_wearing/summary_006.csv
junevis/client/dist/demo/projects/mask_wearing/summary_007.csv
junevis/client/dist/demo/projects/mask_wearing/summary_008.csv
junevis/client/dist/demo/projects/mask_wearing/summary_009.csv
junevis/client/dist/demo/projects/mask_wearing/summary_010.csv
junevis/client/dist/demo/projects/mask_wearing/summary_011.csv
junevis-0.0.9.dist-info/LICENSE
junevis-0.0.9.dist-info/METADATA
junevis-0.0.9.dist-info/WHEEL
junevis-0.0.9.dist-info/entry_points.txt
junevis-0.0.9.dist-info/top_level.txt
junevis-0.0.9.dist-info/RECORD
