Metadata-Version: 2.1
Name: junevis
Version: 0.0.9
Summary: A dashboard to analyze the results of the JUNE epidemic and intervention simulator
Home-page: https://github.com/bhoov/JUNE-vis/tree/master/
Author: Benjamin Hoover, Hendrik Strobelt
Author-email: benhoover34@gmail.com
License: Apache Software License 2.0
Keywords: covid simulation epidemic dashboard intervention policy web
Platform: UNKNOWN
Classifier: Development Status :: 3 - Alpha
Classifier: Intended Audience :: Developers
Classifier: License :: OSI Approved :: Apache Software License
Classifier: Natural Language :: English
Classifier: Programming Language :: Python :: 3.6
Classifier: Programming Language :: Python :: 3.7
Classifier: Programming Language :: Python :: 3.8
Requires-Python: >=3.6
Requires-Dist: pandas
Requires-Dist: numpy
Requires-Dist: tables
Requires-Dist: geopandas
Requires-Dist: matplotlib
Requires-Dist: descartes
Requires-Dist: fastapi[all] (==0.54.1)
